Products.PortalTransforms-4.1.1-py3.12-nspkg.pth
Products/PortalTransforms/Transform.py
Products/PortalTransforms/TransformEngine.py
Products/PortalTransforms/TransformTool.py
Products/PortalTransforms/__init__.py
Products/PortalTransforms/cache.py
Products/PortalTransforms/chain.py
Products/PortalTransforms/configure.zcml
Products/PortalTransforms/data.py
Products/PortalTransforms/interfaces.py
Products/PortalTransforms/setuphandlers.py
Products/PortalTransforms/testing.py
Products/PortalTransforms/tool.gif
Products/PortalTransforms/utils.py
Products/PortalTransforms/libtransforms/__init__.py
Products/PortalTransforms/libtransforms/commandtransform.py
Products/PortalTransforms/libtransforms/piltransform.py
Products/PortalTransforms/libtransforms/retransform.py
Products/PortalTransforms/libtransforms/utils.py
Products/PortalTransforms/profiles/default/componentregistry.xml
Products/PortalTransforms/profiles/default/import_steps.xml
Products/PortalTransforms/profiles/default/metadata.xml
Products/PortalTransforms/profiles/default/portal-transforms-various.txt
Products/PortalTransforms/profiles/default/toolset.xml
Products/PortalTransforms/tests/__init__.py
Products/PortalTransforms/tests/base.py
Products/PortalTransforms/tests/test_doctests.py
Products/PortalTransforms/tests/test_engine.py
Products/PortalTransforms/tests/test_graph.py
Products/PortalTransforms/tests/test_intelligenttext.py
Products/PortalTransforms/tests/test_js_uri.html
Products/PortalTransforms/tests/test_transforms.py
Products/PortalTransforms/tests/test_xss.py
Products/PortalTransforms/tests/utils.py
Products/PortalTransforms/tests/input/demo1.pdf
Products/PortalTransforms/tests/input/input.textile
Products/PortalTransforms/tests/input/logo.bmp
Products/PortalTransforms/tests/input/logo.gif
Products/PortalTransforms/tests/input/logo.jpg
Products/PortalTransforms/tests/input/logo.png
Products/PortalTransforms/tests/input/markdown.txt
Products/PortalTransforms/tests/input/org-news.xml
Products.PortalTransforms-4.1.1.dist-info/METADATA
Products.PortalTransforms-4.1.1.dist-info/WHEEL
Products.PortalTransforms-4.1.1.dist-info/namespace_packages.txt
Products.PortalTransforms-4.1.1.dist-info/top_level.txt
Products.PortalTransforms-4.1.1.dist-info/RECORD
