Metadata-Version: 2.1
Name: Products.PortalTransforms
Version: 4.1.1
Summary: MIME based content transformations
Home-page: https://pypi.org/project/Products.PortalTransforms
Author: Benjamin Saller
Author-email: plone-developers@lists.sourceforge.net
License: GPL
Keywords: Zope Plone Transform
Classifier: Development Status :: 5 - Production/Stable
Classifier: Environment :: Web Environment
Classifier: Framework :: Plone
Classifier: Framework :: Plone :: 6.0
Classifier: Framework :: Plone :: Core
Classifier: Framework :: Zope :: 5
Classifier: License :: OSI Approved :: GNU General Public License (GPL)
Classifier: Operating System :: OS Independent
Classifier: Programming Language :: Python
Classifier: Programming Language :: Python :: 3.8
Classifier: Programming Language :: Python :: 3.9
Classifier: Programming Language :: Python :: 3.10
Classifier: Programming Language :: Python :: 3.11
Requires-Python: >=3.8
Requires-Dist: docutils
Requires-Dist: DocumentTemplate
Requires-Dist: Persistence
Requires-Dist: Products.GenericSetup
Requires-Dist: setuptools
Requires-Dist: lxml
Requires-Dist: lxml-html-clean
Requires-Dist: persistent
Requires-Dist: plone.base
Requires-Dist: plone.registry
Requires-Dist: plone.intelligenttext
Requires-Dist: zope.structuredtext
Requires-Dist: Pillow>=3.1.0
Requires-Dist: Products.CMFCore
Requires-Dist: Products.MimetypesRegistry
Requires-Dist: Zope
Requires-Dist: Markdown>=2.6.5
Provides-Extra: test
Requires-Dist: plone.app.contenttypes[test]; extra == "test"
Requires-Dist: plone.app.testing; extra == "test"
